anvil/__init__.py
anvil/chain.py
anvil/cli.py
anvil/core.py
anvil/credentials.py
anvil/jit_generator.py
anvil/loader.py
anvil/logger.py
anvil/models.py
anvil/sandbox.py
anvil/tool_manager.py
anvil/adapters/__init__.py
anvil/adapters/autogen.py
anvil/adapters/crewai.py
anvil/adapters/langchain.py
anvil/adapters/openai_agents.py
anvil/generators/__init__.py
anvil/generators/base.py
anvil/generators/local.py
anvil/generators/stub.py
anvil/llm/__init__.py
anvil/llm/anthropic.py
anvil/llm/grok.py
anvil/llm/openai.py
anvil/llm/provider.py
anvil_agent-0.1.1.dist-info/METADATA
anvil_agent-0.1.1.dist-info/WHEEL
anvil_agent-0.1.1.dist-info/entry_points.txt
anvil_agent-0.1.1.dist-info/licenses/LICENSE
anvil_agent-0.1.1.dist-info/RECORD
