Metadata-Version: 2.4
Name: anvil-agent
Version: 0.1.1
Summary: JIT Infrastructure & Self-Healing SDK for AI Agents - Generate tools on the fly with BYO API keys
Project-URL: Homepage, https://github.com/Kart-ing/anvil-sdk
Project-URL: Documentation, https://github.com/Kart-ing/anvil-sdk#readme
Project-URL: Repository, https://github.com/Kart-ing/anvil-sdk
Author: Anvil Team
License-Expression: MIT
License-File: LICENSE
Keywords: agents,ai,jit,llm,sdk,self-healing,tools
Classifier: Development Status :: 4 - Beta
Classifier: Intended Audience :: Developers
Classifier: License :: OSI Approved :: MIT License
Classifier: Programming Language :: Python :: 3
Classifier: Programming Language :: Python :: 3.10
Classifier: Programming Language :: Python :: 3.11
Classifier: Programming Language :: Python :: 3.12
Classifier: Topic :: Software Development :: Libraries :: Python Modules
Requires-Python: >=3.10
Requires-Dist: click>=8.0.0
Requires-Dist: httpx>=0.25.0
Requires-Dist: python-dotenv>=1.0.0
Requires-Dist: rich>=13.0.0
Provides-Extra: all
Requires-Dist: anthropic>=0.40.0; extra == 'all'
Requires-Dist: autogen-core>=0.4.0; extra == 'all'
Requires-Dist: crewai>=0.1.0; extra == 'all'
Requires-Dist: firecrawl-py>=1.0.0; extra == 'all'
Requires-Dist: langchain-core>=0.1.0; extra == 'all'
Requires-Dist: openai-agents>=0.0.1; extra == 'all'
Requires-Dist: openai>=1.0.0; extra == 'all'
Provides-Extra: all-frameworks
Requires-Dist: autogen-core>=0.4.0; extra == 'all-frameworks'
Requires-Dist: crewai>=0.1.0; extra == 'all-frameworks'
Requires-Dist: langchain-core>=0.1.0; extra == 'all-frameworks'
Requires-Dist: openai-agents>=0.0.1; extra == 'all-frameworks'
Provides-Extra: all-providers
Requires-Dist: anthropic>=0.40.0; extra == 'all-providers'
Requires-Dist: firecrawl-py>=1.0.0; extra == 'all-providers'
Requires-Dist: openai>=1.0.0; extra == 'all-providers'
Provides-Extra: anthropic
Requires-Dist: anthropic>=0.40.0; extra == 'anthropic'
Provides-Extra: autogen
Requires-Dist: autogen-core>=0.4.0; extra == 'autogen'
Provides-Extra: crewai
Requires-Dist: crewai>=0.1.0; extra == 'crewai'
Provides-Extra: dev
Requires-Dist: anthropic>=0.40.0; extra == 'dev'
Requires-Dist: build>=1.0.0; extra == 'dev'
Requires-Dist: firecrawl-py>=1.0.0; extra == 'dev'
Requires-Dist: mypy>=1.0.0; extra == 'dev'
Requires-Dist: openai>=1.0.0; extra == 'dev'
Requires-Dist: pytest-asyncio>=0.21.0; extra == 'dev'
Requires-Dist: pytest>=7.0.0; extra == 'dev'
Requires-Dist: twine>=5.0.0; extra == 'dev'
Provides-Extra: firecrawl
Requires-Dist: firecrawl-py>=1.0.0; extra == 'firecrawl'
Provides-Extra: langchain
Requires-Dist: langchain-core>=0.1.0; extra == 'langchain'
Provides-Extra: openai
Requires-Dist: openai>=1.0.0; extra == 'openai'
Provides-Extra: openai-agents
Requires-Dist: openai-agents>=0.0.1; extra == 'openai-agents'
